tornado-requests/__init__.py
tornado-requests/tornado_requests.py
tornado_requests/__init__.py
tornado_requests/tornado_requests.py
tornado_requests-0.1.4.dist-info/LICENSE
tornado_requests-0.1.4.dist-info/METADATA
tornado_requests-0.1.4.dist-info/WHEEL
tornado_requests-0.1.4.dist-info/top_level.txt
tornado_requests-0.1.4.dist-info/RECORD
